{
	"world": 6,
	"subworld": 3,
	"enemy_context": ["subs"],
	"nodes": {
		"A": {
			"coords": [331, 322],
			"types": ["select"]
		},
		"B": {
			"coords": [378, 214],
			"types": ["sub"]
		},
		"C": {
			"coords": [436, 444],
			"types": ["sub"]
		},
		"D": {
			"coords": [506, 188]
		},
		"E": {
			"coords": [580, 311]
		},
		"F": {
			"coords": [726, 474]
		},
		"J": {
			"coords": [990, 263],
			"types": ["boss"]
		}
	},
	"edges": {
		"1": ["Start", "A"],
		"2": ["A", "B"],
		"3": ["A", "C"],
		"4": ["B", "D"],
		"5": ["C", "E"],
		"6": ["E", "F"],
		"7": ["E", "G"],
		"8": ["F", "H"],
		"9": ["H", "I"],
		"10": ["H", "J"],
		"11": ["D", "E"],
		"12": ["G", "H"]
	}
}
