{
	"world": 6,
	"subworld": 4,
	"quest_context": ["carriers", "subs"],
	"nodes": {
		"A": {
			"coords": [249, 215]
		},
		"B": {
			"coords": [263, 403]
		},
		"C": {
			"coords": [387, 486]
		},
		"D": {
			"coords": [434, 306],
			"types": ["air"]
		},
		"E": {
			"coords": [475, 173]
		},
		"F": {
			"coords": [538, 498],
			"types": ["air"]
		},
		"G": {
			"coords": [605, 264],
			"types": ["air"]
		},
		"H": {
			"coords": [705, 529]
		},
		"I": {
			"coords": [773, 229],
			"types": ["air"]
		},
		"J": {
			"coords": [790, 389]
		},
		"K": {
			"coords": [891, 509]
		},
		"L": {
			"coords": [900, 281]
		},
		"M": {
			"coords": [978, 396],
			"types": ["sub"]
		},
		"N": {
			"coords": [622, 392],
			"types": ["boss"]
		}
	}
}
